btw/History.py
btw/User.py
btw/__init__.py
btw/__main__.py
btw/ai.py
btw/config.py
btw/const.py
btw/log.py
btw/openai.py
btw-1.0.7.dist-info/METADATA
btw-1.0.7.dist-info/WHEEL
btw-1.0.7.dist-info/entry_points.txt
btw-1.0.7.dist-info/top_level.txt
btw-1.0.7.dist-info/RECORD
