Metadata-Version: 2.1
Name: btw
Version: 1.0.7
Summary: By The Way is an NLP command line powered by openai
Home-page: https://github.com/bidetaggle/btw
Author: bidetaggle
Author-email: bidetaggle@gmail.com
License: MIT
Platform: UNKNOWN
Classifier: License :: OSI Approved :: MIT License
Classifier: Programming Language :: Python :: 3
Classifier: Programming Language :: Python :: 3.7
Requires-Dist: wheel
Requires-Dist: openai
Requires-Dist: toml
Requires-Dist: colored
Requires-Dist: inquirer
